vpic/__init__.py
vpic/client.py
vpic/client_base.py
vpic/exceptions.py
vpic/models.py
vpic/py.typed
vpic/session.py
vpic/transforms.py
vpic/typed_client.py
vpic_api-0.7.4.dist-info/LICENSE
vpic_api-0.7.4.dist-info/WHEEL
vpic_api-0.7.4.dist-info/METADATA
vpic_api-0.7.4.dist-info/RECORD
