Metadata-Version: 2.1
Name: vpic-api
Version: 0.7.4
Summary: A client library for the United States National Highway Traffic Safety Administration (NHTSA) Vehicle Product Information Catalog (vPIC) API
Home-page: https://github.com/davidpeckham/vpic-api
License: MIT
Keywords: vpic,nhtsa,vin,vehicle
Author: David Peckham
Author-email: dave.peckham@icloud.com
Requires-Python: >=3.7,<4.0
Classifier: Development Status :: 3 - Alpha
Classifier: License :: OSI Approved :: MIT License
Classifier: Programming Language :: Python :: 3
Classifier: Programming Language :: Python :: 3.7
Classifier: Programming Language :: Python :: 3.8
Classifier: Programming Language :: Python :: 3.9
Classifier: Topic :: Software Development :: Libraries :: Python Modules
Requires-Dist: desert (>=2020.11.18,<2021.0.0)
Requires-Dist: requests (>=2.25.1,<3.0.0)
Project-URL: Documentation, https://davidpeckham.github.io/vpic-api/
Project-URL: Repository, https://github.com/davidpeckham/vpic-api
